prisma_to_sqlmodel/__init__.py
prisma_to_sqlmodel/__main__.py
prisma_to_sqlmodel/cli.py
prisma_to_sqlmodel/py.typed
prisma_to_sqlmodel-0.1.0.dist-info/METADATA
prisma_to_sqlmodel-0.1.0.dist-info/WHEEL
prisma_to_sqlmodel-0.1.0.dist-info/entry_points.txt
prisma_to_sqlmodel-0.1.0.dist-info/licenses/LICENSE
prisma_to_sqlmodel-0.1.0.dist-info/RECORD
