Metadata-Version: 2.4
Name: prisma-to-sqlmodel
Version: 0.1.0
Summary: Convert Prisma schema to SQLModel models
Author-email: Jacob <jacobfv123@gmail.com>
License-File: LICENSE
Requires-Python: >=3.12
Requires-Dist: black>=23.0.0
Requires-Dist: click>=8.0.0
Requires-Dist: numpy>=1.24.0
Requires-Dist: pgvector>=0.2.0
Requires-Dist: sqlalchemy>=2.0.0
Requires-Dist: sqlmodel>=0.0.14
Provides-Extra: dev
Requires-Dist: mypy>=1.0.0; extra == 'dev'
Requires-Dist: pytest-cov>=4.0.0; extra == 'dev'
Requires-Dist: pytest>=7.0.0; extra == 'dev'
Requires-Dist: ruff>=0.1.0; extra == 'dev'
